odoo/addons/account_bank_reconciliation_summary_xlsx/README.rst
odoo/addons/account_bank_reconciliation_summary_xlsx/__init__.py
odoo/addons/account_bank_reconciliation_summary_xlsx/__manifest__.py
odoo/addons/account_bank_reconciliation_summary_xlsx/i18n/account_bank_reconciliation_summary_xlsx.pot
odoo/addons/account_bank_reconciliation_summary_xlsx/i18n/ca.po
odoo/addons/account_bank_reconciliation_summary_xlsx/i18n/fr.po
odoo/addons/account_bank_reconciliation_summary_xlsx/models/__init__.py
odoo/addons/account_bank_reconciliation_summary_xlsx/models/account_move_line.py
odoo/addons/account_bank_reconciliation_summary_xlsx/readme/CONFIGURE.rst
odoo/addons/account_bank_reconciliation_summary_xlsx/readme/CONTRIBUTORS.rst
odoo/addons/account_bank_reconciliation_summary_xlsx/readme/DESCRIPTION.rst
odoo/addons/account_bank_reconciliation_summary_xlsx/readme/USAGE.rst
odoo/addons/account_bank_reconciliation_summary_xlsx/report/__init__.py
odoo/addons/account_bank_reconciliation_summary_xlsx/report/bank_reconciliation_xlsx.py
odoo/addons/account_bank_reconciliation_summary_xlsx/report/report.xml
odoo/addons/account_bank_reconciliation_summary_xlsx/static/description/icon.png
odoo/addons/account_bank_reconciliation_summary_xlsx/static/description/index.html
odoo/addons/account_bank_reconciliation_summary_xlsx/views/account_bank_statement.xml
odoo/addons/account_bank_reconciliation_summary_xlsx/views/account_journal.xml
odoo/addons/account_bank_reconciliation_summary_xlsx/views/account_move_line.xml
odoo/addons/account_bank_reconciliation_summary_xlsx/wizard/__init__.py
odoo/addons/account_bank_reconciliation_summary_xlsx/wizard/bank_reconciliation_report_wizard.py
odoo/addons/account_bank_reconciliation_summary_xlsx/wizard/bank_reconciliation_report_wizard_view.xml
odoo13_addon_account_bank_reconciliation_summary_xlsx-13.0.1.0.1.dist-info/METADATA
odoo13_addon_account_bank_reconciliation_summary_xlsx-13.0.1.0.1.dist-info/WHEEL
odoo13_addon_account_bank_reconciliation_summary_xlsx-13.0.1.0.1.dist-info/top_level.txt
odoo13_addon_account_bank_reconciliation_summary_xlsx-13.0.1.0.1.dist-info/RECORD
